pymellon/__init__.py
pymellon/auth.py
pymellon/command.py
pymellon/management.py
pymellon/ports.py
pymellon-0.2.16.dist-info/LICENSE
pymellon-0.2.16.dist-info/METADATA
pymellon-0.2.16.dist-info/WHEEL
pymellon-0.2.16.dist-info/top_level.txt
pymellon-0.2.16.dist-info/RECORD
