Metadata-Version: 2.1
Name: pymellon
Version: 0.2.16
Summary: A python binding to work with the Mellanox API
Home-page: https://github.com/xod442/pymellon
Download-URL: https://github.com/xod442/pymellon/archive/refs/tags/v.0.2.16.tar.gz
Author: Rick Kauffman
Author-email: rick@rickkauffman.com
Keywords: mellanox,api,python
License-File: LICENSE
